frsystem/__init__.py
frsystem/frs.py
frsystem/helper.py
frsystem/models.py
frsystem/version.py
frsystem/vggface.py
frsystem-1.1.3.dist-info/METADATA
frsystem-1.1.3.dist-info/WHEEL
frsystem-1.1.3.dist-info/top_level.txt
frsystem-1.1.3.dist-info/RECORD
