Metadata-Version: 2.1
Name: frsystem
Version: 1.1.3
Summary: A system for experimenting with face recognition
Home-page: https://github.com/amac-lfc/frsystem
Author: Arnur Sabet
Author-email: arnursabet@gmail.com
License: GNU GENERAL PUBLIC LICENSE
Platform: UNKNOWN
